orphe/__init__.py
orphe/_analytics.py
orphe/_filter.py
orphe/_gait.py
orphe/_pose.py
orphe/_unit.py
orphe-0.1.10.dist-info/METADATA
orphe-0.1.10.dist-info/WHEEL
orphe-0.1.10.dist-info/top_level.txt
orphe-0.1.10.dist-info/RECORD
