Metadata-Version: 2.4
Name: orphe
Version: 0.1.10
Summary: ORPHE ANALYTICIS SDK for Python
Author-email: "ORPHE Inc." <support@orphe.io>
License-Expression: Apache-2.0
Project-URL: Homepage, https://orphe.io/
Keywords: orphe,orphe analytics
Classifier: Development Status :: 4 - Beta
Classifier: Intended Audience :: Developers
Classifier: Programming Language :: Python :: 3
Classifier: Programming Language :: Python :: 3.5
Classifier: Programming Language :: Python :: 3.6
Classifier: Programming Language :: Python :: 3.7
Classifier: Programming Language :: Python :: 3.8
Classifier: Programming Language :: Python :: 3.9
Classifier: Programming Language :: Python :: 3.10
Classifier: Programming Language :: Python :: 3.11
Classifier: Programming Language :: Python :: 3.12
Classifier: Programming Language :: Python :: 3.13
Requires-Python: >=3.5
Requires-Dist: intdash
Requires-Dist: numpy
Requires-Dist: pandas
